tuyacloud/TuyaCloudClient.py
tuyacloud/TuyaCloudClientExceptions.py
tuyacloud/TuyaCloudClientNicer.py
tuyacloud/__init__.py
tuyacloud-1.0.1.dist-info/METADATA
tuyacloud-1.0.1.dist-info/WHEEL
tuyacloud-1.0.1.dist-info/licenses/LICENSE
tuyacloud-1.0.1.dist-info/RECORD
