Metadata-Version: 2.1
Name: tuyacloud
Version: 1.0.1
Summary: Tuya Cloud Client package based on http-API for Tuya IoT Development Platform
Project-URL: Homepage, https://github.com/mrtxee/tuyacloud
Project-URL: Bug Tracker, https://github.com/mrtxee/tuyacloud/issues
Author-email: Artem Mironov <mrtxee@gmail.com>
License-File: LICENSE
Keywords: api,client,http,iot,samrthome,tuya
Classifier: License :: OSI Approved :: GNU General Public License v3 (GPLv3)
Classifier: Operating System :: OS Independent
Classifier: Programming Language :: Python :: 3
Requires-Python: >=3.0
